<?xml version="1.0" encoding="utf-8" ?>
<parameters>
  <CreateUsersInBulk>
    <url>https://dev-srv-wso2-02.westeurope.cloudapp.azure.com:9443/scim2/Bulk</url>
    <contentType>application/json</contentType>
    <method>POST</method>
    <username>admin@wso2.com</username>
    <password>admin</password>
    <maxSizeStart>1000</maxSizeStart>
  </CreateUsersInBulk>
  <SCIMcheckData>
    <url>https://dev-srv-wso2-02.westeurope.cloudapp.azure.com:9443/scim2/Users/</url>
    <contentType></contentType>
    <method>GET</method>
    <username>admin@wso2.com</username>
    <password>admin</password>
  </SCIMcheckData>
</parameters>